nh_lib/__init__.py
nh_lib/script_librerias.py
nh_lib-0.1.5.dist-info/licenses/LICENSE
nh_lib-0.1.5.dist-info/METADATA
nh_lib-0.1.5.dist-info/WHEEL
nh_lib-0.1.5.dist-info/top_level.txt
nh_lib-0.1.5.dist-info/RECORD
